package/__init__.py
package/auth_deco.py
timauthdecpkg/__init__.py
timauthdecpkg/auth_deco.py
timauthdecpkg-0.0.2.dist-info/METADATA
timauthdecpkg-0.0.2.dist-info/WHEEL
timauthdecpkg-0.0.2.dist-info/top_level.txt
timauthdecpkg-0.0.2.dist-info/RECORD
