Metadata-Version: 2.1
Name: timauthdecpkg
Version: 0.0.2
Summary: JWT token authentication decorator
Home-page: UNKNOWN
Author: KE
Author-email: 
License: UNKNOWN
Keywords: python,flask,JWT,decorator,token
Platform: UNKNOWN
Classifier: Development Status :: 1 - Planning
Classifier: Intended Audience :: Developers
Classifier: Programming Language :: Python :: 3.11
Classifier: Operating System :: Unix
Classifier: Operating System :: MacOS
Requires-Dist: flask
